thumbalizr_tags.py
Thumablizr_tags-1.0.1.data/scripts/settings.py
Thumablizr_tags-1.0.1.data/scripts/thumbalizr_tags.py
Thumablizr_tags-1.0.1.dist-info/METADATA
Thumablizr_tags-1.0.1.dist-info/WHEEL
Thumablizr_tags-1.0.1.dist-info/top_level.txt
Thumablizr_tags-1.0.1.dist-info/RECORD
