Metadata-Version: 2.1
Name: Thumablizr-tags
Version: 1.0.1
Summary: Use Thumbalizr in your Django templates
Home-page: https://github.com/juliensobrier/thumbalizr_django
Author: Julien Sobrier
Author-email: julien@sobrier.net
License: Apache
Platform: UNKNOWN
Classifier: Development Status :: 4 - Beta
Classifier: Environment :: Console
Classifier: Intended Audience :: Developers
Classifier: Intended Audience :: Information Technology
Classifier: License :: OSI Approved :: BSD License
Classifier: Operating System :: OS Independent
Classifier: Programming Language :: Python
Requires-Dist: thumbalizr
